scicam/__init__.py
scicam/_version.py
scicam/configuration.py
scicam/constants.py
scicam/decorators.py
scicam/exceptions.py
scicam/utils.py
scicam/bin/__init__.py
scicam/bin/__main__.py
scicam/bin/grabmultiplecameras.py
scicam/bin/run.py
scicam/bin/test.py
scicam/bin/test_queue.py
scicam/class_utils/__init__.py
scicam/class_utils/time.py
scicam/core/__init__.py
scicam/core/manager.py
scicam/core/monitor.py
scicam/io/__init__.py
scicam/io/cameras/__init__.py
scicam/io/cameras/__main__.py
scicam/io/cameras/core.py
scicam/io/cameras/dlc.py
scicam/io/cameras/flir.py
scicam/io/cameras/opencv.py
scicam/io/cameras/plugins.py
scicam/io/cameras/setup.py
scicam/io/cameras/utils.py
scicam/io/cameras/basler/__init__.py
scicam/io/cameras/basler/__main__.py
scicam/io/cameras/basler/basler.py
scicam/io/cameras/basler/compat.py
scicam/io/cameras/basler/parser.py
scicam/io/recorders/__init__.py
scicam/io/recorders/__main__.py
scicam/io/recorders/core.py
scicam/io/recorders/imgstore.py
scicam/io/recorders/parser.py
scicam/io/recorders/record.py
scicam/io/recorders/mixins/__init__.py
scicam/io/recorders/mixins/ffmpeg.py
scicam/io/recorders/mixins/opencv.py
scicam/tests/__init__.py
scicam/tests/test_basler.py
scicam/tests/test_recorder.py
scicam/tests/test_synchrony.py
scicam/tests/utils.py
scicam/web_utils/__init__.py
scicam/web_utils/client.py
scicam/web_utils/sensor.py
scicam/web_utils/server.py
scicam-0.1.3.dist-info/METADATA
scicam-0.1.3.dist-info/WHEEL
scicam-0.1.3.dist-info/entry_points.txt
scicam-0.1.3.dist-info/top_level.txt
scicam-0.1.3.dist-info/RECORD
