Metadata-Version: 2.1
Name: scicam
Version: 0.1.3
Requires-Python: >=3.8
Requires-Dist: numpy (==1.19.5)
Requires-Dist: pandas (>=1.2.4)
Requires-Dist: joblib (>=1.1.0)
Requires-Dist: opencv-python (==4.5.1.48)
Requires-Dist: pyaml (>=6.0)
Requires-Dist: pypylon (>=1.8.0)
Requires-Dist: simple-pyspin (>=0.1.1)
Requires-Dist: imgstore-shaliulab (>=0.4.8)
Requires-Dist: scikit-video (>=1.1.11)
Requires-Dist: arrayqueues (>=1.3.0)
